encoders/__init__.py
encoders/base_encoder.py
encoders/cache_encoder.py
encoders/composite_encoder.py
encoders/dump_cache_utils.py
encoders/encoder_factory.py
encoders/encoders_constants.py
encoders/adapters/__init__.py
encoders/adapters/bert_embedded_adapter.py
encoders/adapters/bert_thin_client_encoder_adapter.py
encoders/adapters/tf_idf_encoder_adapter.py
encoder_lib-1.3.dist-info/LICENSE
encoder_lib-1.3.dist-info/METADATA
encoder_lib-1.3.dist-info/WHEEL
encoder_lib-1.3.dist-info/top_level.txt
encoder_lib-1.3.dist-info/RECORD
