Metadata-Version: 2.1
Name: encoder-lib
Version: 1.3
Summary: Library for creating encoders pipes
Home-page: https://github.com/NightFantom/encoder_lib
Author: Denis Usachev
Author-email: usachevdy@yandex.ru
License: UNKNOWN
Platform: UNKNOWN
Classifier: Programming Language :: Python :: 3
Classifier: Operating System :: OS Independent
Requires-Python: >=3.6
Provides-Extra: bert_client
Requires-Dist: bert-serving-client (==1.10.0) ; extra == 'bert_client'
Provides-Extra: bert_embedded
Requires-Dist: bert-experimental (==1.0.4) ; extra == 'bert_embedded'
